{
  "title": "Dolphin",
  "color": ["various colors"],
  "feature": ["sleek body", "blowhole", "fin"],
  "geolocation": ["oceans", "seas"],
  "use": ["ecosystem balance", "tourism"],
  "measurement": ["length: varies depending on species"],
  "origin": ["oceans", "seas"],
  "special_behavior": [
    "highly intelligent",
    "social",
    "communicate with clicks and whistles"
  ],
  "speed": ["varies depending on species"],
  "age": ["lifespan varies depending on species"],
  "communication": ["vocalizations", "body language"],
  "conservation_status": ["varies depending on species"],
  "habitat": ["oceans", "seas"],
  "diet": ["carnivorous", "fish", "squid"],
  "predators": ["sharks", "killer whales"],
  "facts": [
    "known for their agility and acrobatic behaviors",
    "form complex social structures and communicate effectively",
    "have excellent echolocation abilities",
    "highly sensitive to their environment"
  ]
}
