{
  "title": "Raccoon",
  "visual": ["medium size", "masked face", "ringed tail"],
  "about": [
    "mammal species native to North America",
    "omnivorous diet",
    "lifespan: up to 3-5 years in the wild"
  ],
  "geolocation": ["North America"],
  "measurement": ["length: up to 2-3 ft", "weight: up to 10-20 lbs"],
  "communication": ["chittering sounds", "body language"],
  "other": [
    "nocturnal and adaptable behavior",
    "skillful climbers and foragers",
    "known for their dexterity and intelligence",
    "urban adaptability and scavenging abilities"
  ]
}
